bugscan_x-2.0.7.dist-info/licenses/LICENSE
bugscanx/__init__.py
bugscanx/handler.py
bugscanx/main.py
bugscanx/modules/others/dns_records.py
bugscanx/modules/others/file_toolkit.py
bugscanx/modules/others/help.py
bugscanx/modules/others/host_info.py
bugscanx/modules/others/update.py
bugscanx/modules/scanners/host_scanner.py
bugscanx/modules/scanners/port_scanner.py
bugscanx/modules/scanners/scanners/base.py
bugscanx/modules/scanners/scanners/direct.py
bugscanx/modules/scanners/scanners/multithread.py
bugscanx/modules/scanners/scanners/ping.py
bugscanx/modules/scanners/scanners/proxy_check.py
bugscanx/modules/scanners/scanners/proxy_request.py
bugscanx/modules/scanners/scanners/ssl.py
bugscanx/modules/scrapers/iplookup/iplookup.py
bugscanx/modules/scrapers/iplookup/logger.py
bugscanx/modules/scrapers/iplookup/sources.py
bugscanx/modules/scrapers/iplookup/utils.py
bugscanx/modules/scrapers/subfinder/logger.py
bugscanx/modules/scrapers/subfinder/sources.py
bugscanx/modules/scrapers/subfinder/subfinder.py
bugscanx/modules/scrapers/subfinder/utils.py
bugscanx/utils/config.py
bugscanx/utils/http.py
bugscanx/utils/prompts.py
bugscanx/utils/validators.py
tests/scrapers/iplookup/test_iplookup.py
tests/scrapers/iplookup/test_sources.py
tests/scrapers/subfinder/test_sources.py
tests/scrapers/subfinder/test_subfinder.py
bugscan_x-2.0.7.dist-info/METADATA
bugscan_x-2.0.7.dist-info/WHEEL
bugscan_x-2.0.7.dist-info/entry_points.txt
bugscan_x-2.0.7.dist-info/top_level.txt
bugscan_x-2.0.7.dist-info/RECORD
