Metadata-Version: 2.4
Name: bugscan-x
Version: 2.0.7
Summary: All-in-one tool for SNI discovery
Author-email: Ayan Rajpoot <ayanrajpoot2004@gmail.com>
License: MIT
Project-URL: Homepage, https://github.com/Ayanrajpoot10/bugscanx
Keywords: sni,scanning-tool,subdomain-enumeration,bughost,cidr-scanning,reverse-ip-lookup
Classifier: License :: OSI Approved :: MIT License
Classifier: Operating System :: OS Independent
Classifier: Programming Language :: Python :: 3
Requires-Python: >=3.7
License-File: LICENSE
Requires-Dist: beautifulsoup4
Requires-Dist: dnspython
Requires-Dist: InquirerPy
Requires-Dist: packaging
Requires-Dist: pyfiglet
Requires-Dist: requests
Requires-Dist: rich
Requires-Dist: tqdm
Dynamic: license-file
